mtse/__init__.py
mtse/attention.py
mtse/data_utils.py
mtse/decoders.py
mtse/demo.py
mtse/encoders.py
mtse/import torch.py
mtse/load_data.py
mtse/model_utils.py
mtse/models.py
mtse/utils.py
mtse/data/norm.pkl
mtse/data/test.pkl
mtse/data/train.pkl
mtse/data/val.pkl
mtse-0.1.6.dist-info/METADATA
mtse-0.1.6.dist-info/WHEEL
mtse-0.1.6.dist-info/top_level.txt
mtse-0.1.6.dist-info/RECORD
