Metadata-Version: 2.1
Name: mtse
Version: 0.1.6
Summary: Multi Time Series Encoders
Home-page: https://github.com/FractalySyn/mtse
Author: FractalySyn (Corentin Lobet)
Author-email: <corentin.lobet@etu.unistra.fr>
License: Apache 2.0
Platform: UNKNOWN
Classifier: Development Status :: 1 - Planning
Classifier: Intended Audience :: Developers
Classifier: Programming Language :: Python :: 3
Classifier: Operating System :: Unix
Classifier: Operating System :: MacOS :: MacOS X
Classifier: Operating System :: Microsoft :: Windows
Requires-Python: >=3.7
Requires-Dist: torch (>=1.7)
Requires-Dist: numpy (>=1.19)
Requires-Dist: pandas (>=1.3)
Requires-Dist: matplotlib (>=3.4)
Requires-Dist: setuptools
